pyorganoid/__init__.py
pyorganoid/agents.py
pyorganoid/base.py
pyorganoid/cells.py
pyorganoid/environments.py
pyorganoid/models.py
pyorganoid/modules.py
pyorganoid/onnx_module.py
pyorganoid/organoids.py
pyorganoid/simulation.py
pyorganoid/sklearn_module.py
pyorganoid/tf_module.py
pyorganoid/torch_module.py
pyorganoid/utils.py
pyorganoid-0.1.5.dist-info/LICENSE.md
pyorganoid-0.1.5.dist-info/METADATA
pyorganoid-0.1.5.dist-info/WHEEL
pyorganoid-0.1.5.dist-info/entry_points.txt
pyorganoid-0.1.5.dist-info/top_level.txt
pyorganoid-0.1.5.dist-info/RECORD
