Metadata-Version: 2.1
Name: pyorganoid
Version: 0.1.5
Summary: A Python package for the simulation of organoids for the purpose of studying Organoid Intelligence (OI) and Organoid Learning (OL).
Home-page: https://danielathome19.github.io/pyorganoid
Author: Daniel Szelogowski
Project-URL: Documentation, https://danielathome19.github.io/pyorganoid
Project-URL: Source, https://github.com/danielathome19/pyorganoid
Project-URL: Tracker, https://github.com/danielathome19/pyorganoid/issues
License-File: LICENSE.md
Requires-Dist: numpy
Requires-Dist: matplotlib
Requires-Dist: graphviz
Provides-Extra: all
Requires-Dist: tensorflow <=2.15 ; extra == 'all'
Requires-Dist: torch ; extra == 'all'
Requires-Dist: scikit-learn ; extra == 'all'
Requires-Dist: joblib ; extra == 'all'
Requires-Dist: onnxruntime ; extra == 'all'
Requires-Dist: onnxmltools ; extra == 'all'
Provides-Extra: onnx
Requires-Dist: onnxruntime ; extra == 'onnx'
Requires-Dist: onnxmltools ; extra == 'onnx'
Provides-Extra: sklearn
Requires-Dist: scikit-learn ; extra == 'sklearn'
Requires-Dist: joblib ; extra == 'sklearn'
Provides-Extra: tensorflow
Requires-Dist: tensorflow <=2.15 ; extra == 'tensorflow'
Provides-Extra: torch
Requires-Dist: torch ; extra == 'torch'
